mini_tensorflow/MiniTensorflow.py
mini_tensorflow/__init__.py
MiniTensorflow-0.2.2.dist-info/LICENSE
MiniTensorflow-0.2.2.dist-info/METADATA
MiniTensorflow-0.2.2.dist-info/WHEEL
MiniTensorflow-0.2.2.dist-info/top_level.txt
MiniTensorflow-0.2.2.dist-info/RECORD
